[
  { "name": "澤田勝", "kana": "さわだまさる", "party": "創造みらい半田", "district": "半田市", "sourceUrl": "https://www.city.handa.lg.jp/shisei/gikai/1004472/1004475.html" },
  { "name": "芳金秀展", "kana": "よしかねひでのぶ", "party": "創造みらい半田", "district": "半田市", "sourceUrl": "https://www.city.handa.lg.jp/shisei/gikai/1004472/1004475.html" },
  { "name": "山本裕介", "kana": "やまもとゆうすけ", "party": "創造みらい半田", "district": "半田市", "sourceUrl": "https://www.city.handa.lg.jp/shisei/gikai/1004472/1004475.html" },
  { "name": "鈴木英華", "kana": "すずきえいか", "party": "創造みらい半田", "district": "半田市", "sourceUrl": "https://www.city.handa.lg.jp/shisei/gikai/1004472/1004475.html" },
  { "name": "田中嵩久", "kana": "たなかたかひさ", "party": "創造みらい半田", "district": "半田市", "sourceUrl": "https://www.city.handa.lg.jp/shisei/gikai/1004472/1004475.html" },
  { "name": "石川英之", "kana": "いしかわひでゆき", "party": "創造みらい半田", "district": "半田市", "sourceUrl": "https://www.city.handa.lg.jp/shisei/gikai/1004472/1004475.html" },
  { "name": "鈴木幸彦", "kana": "すずきゆきひこ", "party": "創造みらい半田", "district": "半田市", "sourceUrl": "https://www.city.handa.lg.jp/shisei/gikai/1004472/1004475.html" },
  { "name": "榊原瑞輝", "kana": "さかきばらみずき", "party": "創造みらい半田", "district": "半田市", "sourceUrl": "https://www.city.handa.lg.jp/shisei/gikai/1004472/1004475.html" },
  { "name": "竹内功治", "kana": "たけうちこうじ", "party": "創造みらい半田", "district": "半田市", "sourceUrl": "https://www.city.handa.lg.jp/shisei/gikai/1004472/1004475.html" },
  { "name": "沢田清", "kana": "さわだきよし", "party": "創造みらい半田", "district": "半田市", "sourceUrl": "https://www.city.handa.lg.jp/shisei/gikai/1004472/1004475.html" },
  { "name": "岩田玲子", "kana": "いわたれいこ", "party": "創造みらい半田", "district": "半田市", "sourceUrl": "https://www.city.handa.lg.jp/shisei/gikai/1004472/1004475.html" },
  { "name": "渡邉昭司", "kana": "わたなべしょうじ", "party": "創造みらい半田", "district": "半田市", "sourceUrl": "https://www.city.handa.lg.jp/shisei/gikai/1004472/1004475.html" },
  { "name": "坂井美穂", "kana": "さかいみほ", "party": "公明党", "district": "半田市", "sourceUrl": "https://www.city.handa.lg.jp/shisei/gikai/1004472/1004475.html" },
  { "name": "山田清一", "kana": "やまだせいいち", "party": "公明党", "district": "半田市", "sourceUrl": "https://www.city.handa.lg.jp/shisei/gikai/1004472/1004475.html" },
  { "name": "麻生七海", "kana": "あそうななみ", "party": "公明党", "district": "半田市", "sourceUrl": "https://www.city.handa.lg.jp/shisei/gikai/1004472/1004475.html" },
  { "name": "中村和也", "kana": "なかむらかずや", "party": "つなぐ未来", "district": "半田市", "sourceUrl": "https://www.city.handa.lg.jp/shisei/gikai/1004472/1004475.html" },
  { "name": "小出義一", "kana": "こいでよしかず", "party": "つなぐ未来", "district": "半田市", "sourceUrl": "https://www.city.handa.lg.jp/shisei/gikai/1004472/1004475.html" },
  { "name": "伊藤正興", "kana": "いとうまさおき", "party": "チャレンジはんだ", "district": "半田市", "sourceUrl": "https://www.city.handa.lg.jp/shisei/gikai/1004472/1004475.html" },
  { "name": "國弘秀之", "kana": "くにひろひでゆき", "party": "チャレンジはんだ", "district": "半田市", "sourceUrl": "https://www.city.handa.lg.jp/shisei/gikai/1004472/1004475.html" },
  { "name": "有留麻由", "kana": "ありどめまゆ", "party": "無所属", "district": "半田市", "sourceUrl": "https://www.city.handa.lg.jp/shisei/gikai/1004472/1004475.html" },
  { "name": "新美保博", "kana": "にいみやすひろ", "party": "無所属", "district": "半田市", "sourceUrl": "https://www.city.handa.lg.jp/shisei/gikai/1004472/1004475.html" },
  { "name": "加藤美幸", "kana": "かとうみゆき", "party": "無所属", "district": "半田市", "sourceUrl": "https://www.city.handa.lg.jp/shisei/gikai/1004472/1004475.html" }
]
