[
  { "name": "磯部亮次", "kana": "いそべりょうじ", "party": "自民清風会", "district": "岡崎市", "sourceUrl": "https://www.city.okazaki.lg.jp/shigikai/meibo/1009846.html" },
  { "name": "伊藤正義", "kana": "いとうまさよし", "party": "無所属（参政党）", "district": "岡崎市", "sourceUrl": "https://www.city.okazaki.lg.jp/shigikai/meibo/1009846.html" },
  { "name": "井町圭孝", "kana": "いまちよしたか", "party": "民政クラブ", "district": "岡崎市", "sourceUrl": "https://www.city.okazaki.lg.jp/shigikai/meibo/1009846.html" },
  { "name": "大原昌幸", "kana": "おおはらまさゆき", "party": "無所属", "district": "岡崎市", "sourceUrl": "https://www.city.okazaki.lg.jp/shigikai/meibo/1009846.html" },
  { "name": "荻野秀範", "kana": "おぎのひでのり", "party": "無所属", "district": "岡崎市", "sourceUrl": "https://www.city.okazaki.lg.jp/shigikai/meibo/1009846.html" },
  { "name": "小田高之", "kana": "おだたかゆき", "party": "チャレンジ岡崎", "district": "岡崎市", "sourceUrl": "https://www.city.okazaki.lg.jp/shigikai/meibo/1009846.html" },
  { "name": "加藤史朗", "kana": "かとうふみあき", "party": "自民清風会", "district": "岡崎市", "sourceUrl": "https://www.city.okazaki.lg.jp/shigikai/meibo/1009846.html" },
  { "name": "加藤嘉哉", "kana": "かとうよしや", "party": "民政クラブ", "district": "岡崎市", "sourceUrl": "https://www.city.okazaki.lg.jp/shigikai/meibo/1009846.html" },
  { "name": "加藤義幸", "kana": "かとうよしゆき", "party": "自民清風会", "district": "岡崎市", "sourceUrl": "https://www.city.okazaki.lg.jp/shigikai/meibo/1009846.html" },
  { "name": "金山直樹", "kana": "かなやまなおき", "party": "自民清風会", "district": "岡崎市", "sourceUrl": "https://www.city.okazaki.lg.jp/shigikai/meibo/1009846.html" },
  { "name": "神谷茂樹", "kana": "かみやしげき", "party": "自民清風会", "district": "岡崎市", "sourceUrl": "https://www.city.okazaki.lg.jp/shigikai/meibo/1009846.html" },
  { "name": "酒井正一", "kana": "さかいしょういち", "party": "自民清風会", "district": "岡崎市", "sourceUrl": "https://www.city.okazaki.lg.jp/shigikai/meibo/1009846.html" },
  { "name": "佐藤哲朗", "kana": "さとうてつろう", "party": "民政クラブ", "district": "岡崎市", "sourceUrl": "https://www.city.okazaki.lg.jp/shigikai/meibo/1009846.html" },
  { "name": "柴田敏光", "kana": "しばたとしみつ", "party": "民政クラブ", "district": "岡崎市", "sourceUrl": "https://www.city.okazaki.lg.jp/shigikai/meibo/1009846.html" },
  { "name": "白井正樹", "kana": "しらいまさき", "party": "民政クラブ", "district": "岡崎市", "sourceUrl": "https://www.city.okazaki.lg.jp/shigikai/meibo/1009846.html" },
  { "name": "杉浦久直", "kana": "すぎうらひさなお", "party": "自民清風会", "district": "岡崎市", "sourceUrl": "https://www.city.okazaki.lg.jp/shigikai/meibo/1009846.html" },
  { "name": "杉山智騎", "kana": "すぎやまとものり", "party": "チャレンジ岡崎", "district": "岡崎市", "sourceUrl": "https://www.city.okazaki.lg.jp/shigikai/meibo/1009846.html" },
  { "name": "鈴木静男", "kana": "すずきしずお", "party": "自民清風会", "district": "岡崎市", "sourceUrl": "https://www.city.okazaki.lg.jp/shigikai/meibo/1009846.html" },
  { "name": "鈴木英樹", "kana": "すずきひでき", "party": "民政クラブ", "district": "岡崎市", "sourceUrl": "https://www.city.okazaki.lg.jp/shigikai/meibo/1009846.html" },
  { "name": "鈴木雅子", "kana": "すずきまさこ", "party": "無所属（日本共産党岡崎市議団）", "district": "岡崎市", "sourceUrl": "https://www.city.okazaki.lg.jp/shigikai/meibo/1009846.html" },
  { "name": "瀬戸清太郎", "kana": "せとせいたろう", "party": "民政クラブ", "district": "岡崎市", "sourceUrl": "https://www.city.okazaki.lg.jp/shigikai/meibo/1009846.html" },
  { "name": "田口正夫", "kana": "たぐちまさお", "party": "自民清風会", "district": "岡崎市", "sourceUrl": "https://www.city.okazaki.lg.jp/shigikai/meibo/1009846.html" },
  { "name": "土谷直樹", "kana": "つちやなおき", "party": "公明党", "district": "岡崎市", "sourceUrl": "https://www.city.okazaki.lg.jp/shigikai/meibo/1009846.html" },
  { "name": "中根武彦", "kana": "なかねたけひこ", "party": "自民清風会", "district": "岡崎市", "sourceUrl": "https://www.city.okazaki.lg.jp/shigikai/meibo/1009846.html" },
  { "name": "中根善明", "kana": "なかねよしあき", "party": "無所属（日本共産党岡崎市議団）", "district": "岡崎市", "sourceUrl": "https://www.city.okazaki.lg.jp/shigikai/meibo/1009846.html" },
  { "name": "野島さつき", "kana": "のじまさつき", "party": "公明党", "district": "岡崎市", "sourceUrl": "https://www.city.okazaki.lg.jp/shigikai/meibo/1009846.html" },
  { "name": "野々山雄一郎", "kana": "ののやまゆういちろう", "party": "自民清風会", "district": "岡崎市", "sourceUrl": "https://www.city.okazaki.lg.jp/shigikai/meibo/1009846.html" },
  { "name": "野本篤", "kana": "のもとあつし", "party": "自民清風会", "district": "岡崎市", "sourceUrl": "https://www.city.okazaki.lg.jp/shigikai/meibo/1009846.html" },
  { "name": "畑尻宣長", "kana": "はたじりのりなが", "party": "無所属", "district": "岡崎市", "sourceUrl": "https://www.city.okazaki.lg.jp/shigikai/meibo/1009846.html" },
  { "name": "蜂須賀一郎", "kana": "はちすかいちろう", "party": "自民清風会", "district": "岡崎市", "sourceUrl": "https://www.city.okazaki.lg.jp/shigikai/meibo/1009846.html" },
  { "name": "原紀彦", "kana": "はらのりひこ", "party": "民政クラブ", "district": "岡崎市", "sourceUrl": "https://www.city.okazaki.lg.jp/shigikai/meibo/1009846.html" },
  { "name": "福田澄代", "kana": "ふくだすみよ", "party": "チャレンジ岡崎", "district": "岡崎市", "sourceUrl": "https://www.city.okazaki.lg.jp/shigikai/meibo/1009846.html" },
  { "name": "本多勝", "kana": "ほんだしょう", "party": "無所属", "district": "岡崎市", "sourceUrl": "https://www.city.okazaki.lg.jp/shigikai/meibo/1009846.html" },
  { "name": "前田麗子", "kana": "まえだれいこ", "party": "自民清風会", "district": "岡崎市", "sourceUrl": "https://www.city.okazaki.lg.jp/shigikai/meibo/1009846.html" },
  { "name": "三浦康宏", "kana": "みうらやすひろ", "party": "自民清風会", "district": "岡崎市", "sourceUrl": "https://www.city.okazaki.lg.jp/shigikai/meibo/1009846.html" },
  { "name": "簗瀬太", "kana": "やなせとおる", "party": "自民清風会", "district": "岡崎市", "sourceUrl": "https://www.city.okazaki.lg.jp/shigikai/meibo/1009846.html" },
  { "name": "山村栄", "kana": "やまむらさかえ", "party": "公明党", "district": "岡崎市", "sourceUrl": "https://www.city.okazaki.lg.jp/shigikai/meibo/1009846.html" }
]
